{
  "code": 0,
  "msg": "",
  "count": 1000,
  "data": [
    {
      "id": "1",
      "number": "C-01-001",
      "theme":"春节",
      "title":"春节联谊会、晚会",
      "date": "2017-1-20",
      "place": "活动中心",
      "people": "150",
      "remarks": "无"
    },
    {
      "id": "2",
      "number": "C-01-002",
      "theme":"学雷锋",
      "title":"传统手艺进社区",
      "date": "2017-3-5",
      "place": "社区中心",
      "people": "110",
      "remarks": "无"
    },
    {
      "id": "3",
      "number": "C-01-003",
      "theme":"妇女节",
      "title":"鲜花派送",
      "date": "2017-3-8",
      "place": "妇女联谊会",
      "people": "50",
      "remarks": "无"
    },
    {
      "id": "4",
      "number": "C-01-004",
      "theme":"春分",
      "title":"植树",
      "date": "2017-3-20",
      "place": "郊区",
      "people": "100",
      "remarks": "无"
    },
    {
      "id": "5",
      "number": "C-01-005",
      "theme":"母亲节",
      "title":"我与妈妈的合照",
      "date": "2017-5-14",
      "place": "家中",
      "people": "200",
      "remarks": "无"
    },
    {
      "id": "6",
      "number": "C-01-006",
      "theme":"端午节",
      "title":"百家粽子宴",
      "date": "2017-6-8",
      "place": "社区中心",
      "people": "90",
      "remarks": "无"
    },
    {
      "id": "7",
      "number": "C-01-007",
      "theme":"中秋节",
      "title":"中秋灯谜会",
      "date": "2017-9-14",
      "place": "中央公园",
      "people": "自由",
      "remarks": "无"
    },
    {
      "id": "8",
      "number": "C-01-008",
      "theme":"重阳节",
      "title":"重阳爱心派送",
      "date": "2017-10-7",
      "place": "老年活动中心",
      "people": "110",
      "remarks": "无"
    },
    {
      "id": "9",
      "number": "C-01-009",
      "theme":"知识讲座",
      "title":"心理健康咨询",
      "date": "2017-6-5",
      "place": "社区中心",
      "people": "80",
      "remarks": "无"
    },
    {
      "id": "10",
      "number": "C-01-010",
      "theme":"热心公益",
      "title":"捐资助学",
      "date": "2017-10-20",
      "place": "社区中心",
      "people": "自由",
      "remarks": "无"
    }

  ]
}


